world2vec/__init__.py
world2vec/main.py
world2vec-0.3.0.dist-info/LICENSE.txt
world2vec-0.3.0.dist-info/METADATA
world2vec-0.3.0.dist-info/WHEEL
world2vec-0.3.0.dist-info/entry_points.txt
world2vec-0.3.0.dist-info/top_level.txt
world2vec-0.3.0.dist-info/RECORD
